lucidpy/__init__.py
lucidpy/client.py
lucidpy/models.py
lucidpy-0.1.0.dist-info/METADATA
lucidpy-0.1.0.dist-info/WHEEL
lucidpy-0.1.0.dist-info/licenses/LICENSE
lucidpy-0.1.0.dist-info/RECORD
