Metadata-Version: 2.4
Name: lucidpy
Version: 0.1.0
Summary: A simple python client for the Lucidchart Simple API
Project-URL: Repository, https://github.com/scotho3/lucidpy
Project-URL: Bug Tracker, https://github.com/scotho3/lucidpy/issues
Author-email: Thomas Scott <scotho3@scottho.me>
License: MIT
License-File: LICENSE
Keywords: api,cli,lucid,lucidchart,python
Classifier: Operating System :: OS Independent
Classifier: Programming Language :: Python :: 3
Requires-Python: >=3.12
Requires-Dist: httpx>=0.28.1
Requires-Dist: pre-commit>=4.0.1
Requires-Dist: pydantic>=2.10.5
Requires-Dist: pytest-mock>=3.14.0
Requires-Dist: pytest>=8.3.4
Requires-Dist: rich>=13.9.4
Requires-Dist: toml>=0.10.2
Requires-Dist: typer>=0.15.1
